<?xml version="1.0" encoding="utf-8"?>
<resources>
  <string mz="string" name="string">string</string>
  <string mz="控件名字" name="组件索引">简体中文</string>
  <string mz="L" name="L">L</string>
  <string mz="title" name="9gpz896kp4of6v-n6_fvxn">自由</string>
  <string mz="title" name="9gpz896kqgal3b-n2_kft3">绝对地</string>
  <string mz="title" name="06ybtwdrgki4a-n4_gki4">取消</string>
  <string mz="n2" name="06ybtwdrunhvg-n2_u7at">用脸书登录</string>
  <string mz="n1" name="06ybtwdrunhvh-n1_g7u0">用谷歌登录</string>
  <string mz="n2" name="06ybtwdrgki4b-n2_pnsc">帮助</string>
  <string mz="title" name="06ybtwdrwdfo9-n2_pnsc">再试一次</string>
  <string mz="title" name="06ybtwdrwdfo5-n3_mccl">更新</string>
  <string mz="btn_retry" name="06ybtwdrum1vd-n17_pnsc">再试一次</string>
  <string mz="btn_cancel" name="06ybtwdrum1vd-n24_gki4">帮助</string>
  <string mz="text_title" name="06ybtwdrwdfo0-n28_wb9d">更新</string>
  <string mz="text_tips0" name="06ybtwdrwdfo0-n25_scox">新版本可用。
现在更新！</string>
  <string mz="n7" name="06ybtwdrunhvf-n7_kmcp">登录</string>
  <string mz="text_title" name="06ybtwdrwdfo7-n33_wb9d">没有网络！！！</string>
  <string mz="text_reconnectStatus" name="06ybtwdrwdfo7-n22_b72q">没有网络！！！</string>
  <string mz="text_status" name="06ybtwdrwdfo7-n24_b72q">状态：初始化</string>
  <string mz="n31" name="06ybtwdrwdfo7-n31_mdwa">哎呀，好像有什么
出错！</string>
  <string mz="text_code" name="06ybtwdrxeq4i-n58_rcj0">RRRRRR</string>
  <string mz="title" name="9euvtldhlh5y3j-n1_lh5y">是的</string>
  <string mz="btn_exit" name="9euvtldhlh5y3i-n3_lh5y">不</string>
  <string mz="text_title" name="9euvtldhlh5y3i-n5_lh5y">进入游戏？</string>
  <string mz="text_tips" name="9euvtldhlh5y3i-n6_lh5y">同意&lt;Privacy Policy&gt;后
 和&lt;Terms of Use&gt;，我们可以提供
您拥有游戏服务。确认
 协议？</string>
  <string mz="text_website" name="9euvtldhd4qv0-n14_c6nc">同意&lt;a href='xxx'&gt;隐私政策&lt;/a&gt;和&lt;a href2='xxx2'&gt;条款或使用&lt;/a&gt;</string>
  <string mz="n5" name="5tzgfbiwm9c27-n5_m9c2">再也不会出现</string>
  <string mz="title" name="5tzgfbiwp5cs11-n2_p3x0">好的</string>
  <string mz="text_title" name="5tzgfbiws5oq1q-n1_s5oq">教程</string>
  <string mz="text_tips0" name="5tzgfbiws5oq1q-n2_s5oq">将数字积木移至 PLUS 1，
匹配 3 个相同的数字以合并。</string>
  <string mz="txt" name="sirjnrkkqj6mi-n54_ilew">英语</string>
  <string mz="txt" name="sirjnrkkqj6mp-n61_ilew">英语</string>
  <string mz="title" name="sirjnrkkqj6md-n2_waaa">教程</string>
  <string mz="title" name="sirjnrkkqj6m3-n2_waaa">重新开始</string>
  <string mz="title" name="sirjnrkkqj6m8-n2_waaa">声音开</string>
  <string mz="title" name="sirjnrkkqj6m8-n2_waaa-texts_0">声音开</string>
  <string mz="title" name="sirjnrkkqj6m8-n2_waaa-texts_1">声音关闭</string>
  <string mz="title" name="sirjnrkku4s6t-n2_waaa">振动开启</string>
  <string mz="title" name="sirjnrkku4s6t-n2_waaa-texts_0">振动开启</string>
  <string mz="title" name="sirjnrkku4s6t-n2_waaa-texts_1">振动关</string>
  <string mz="text_title" name="sirjnrkkqj6m0-n14_e5ju">设置</string>
  <string mz="title" name="rl7u9y2lmdwa0-n11_djob">&lt;img src=ui://9gpz896kdjob26&gt;帐户</string>
  <string mz="title" name="rl7u9y2ldjob27-n3_djob">&lt;img src=ui://rl7u9y2ldjob28&gt; [U]改变游戏[/U]</string>
  <string mz="title" name="rl7u9y2lntzg30-n4_ntzg">绝地求生移动</string>
  <string mz="title" name="rl7u9y2lmdwa8-n3_pxc1">确认</string>
  <string mz="title" name="rl7u9y2lmdwa9-n17_pxdq">赎回</string>
  <string mz="title" name="rl7u9y2lmdwac-n3_pxc1">提交图层</string>
  <string mz="text_target" name="rl7u9y2lmdwae-n66_djob">收集 [color=#FF9000]{target=10,000}[/color] 货币</string>
  <string mz="text_target" name="rl7u9y2lmdwae-n66_djob-texts_0">收集 [color=#FF9000]{target=10,000}[/color] 货币</string>
  <string mz="text_target" name="rl7u9y2lmdwae-n66_djob-texts_1">达到等级 [color=#FF9000]{target=10,000}[/color]</string>
  <string mz="text_adTime" name="rl7u9y2lmdwae-n34_u5kg">您必须观看更多 [color=#00CC00]{ad=500}[/color] 视频才能激活订单</string>
  <string mz="text_adTime" name="rl7u9y2lmdwae-n34_u5kg-texts_0">观看 [color=#FF8700]{ad=500}[/color] 视频赢取奖励</string>
  <string mz="text_adTime" name="rl7u9y2lmdwae-n34_u5kg-texts_1">观看视频可将审核时间缩短 [color=#00CC00]{minute=5}[/color] 分钟</string>
  <string mz="text_adTime" name="rl7u9y2lmdwae-n34_u5kg-texts_def">您必须观看更多 [color=#00CC00]{ad=500}[/color] 视频才能激活订单</string>
  <string mz="text_queueText" name="rl7u9y2lmdwae-n69_ntzg">{queuePlayers=9999} 你前面的玩家</string>
  <string mz="text_queueMove" name="rl7u9y2lmdwae-n44_m6sp">您必须观看更多 [color=#00CC00]{ad=500}[/color] 视频才能激活订单</string>
  <string mz="text_queueMove" name="rl7u9y2lmdwae-n44_m6sp-texts_0">一个视频将您带到 [color=#FF8700]{movePlayers=50} [/color] 地点！</string>
  <string mz="text_queueMove" name="rl7u9y2lmdwae-n44_m6sp-texts_def">您必须观看更多 [color=#00CC00]{ad=500}[/color] 视频才能激活订单</string>
  <string mz="text_finish" name="rl7u9y2lmdwae-n70_ntzg">兑换成功！</string>
  <string mz="text_finishWait" name="rl7u9y2lmdwae-n61_iqhi">您将在 [color=#06FF00]7[/color] 个工作日内收到此奖励。</string>
  <string mz="text_successful" name="rl7u9y2lmdwae-n72_ntzg">成功的</string>
  <string mz="n1" name="rl7u9y2ll3r63l-n1_hm08">绝地求生移动</string>
  <string mz="text_title" name="rl7u9y2lu4s63c-n4_u4s6">正在加载</string>
  <string mz="text_tips0" name="rl7u9y2lu4s63c-n5_u4s6">连接服务器...</string>
  <string mz="text_tips1" name="rl7u9y2lu4s63c-n6_u4s6">提交账号...</string>
  <string mz="text_tips2" name="rl7u9y2lu4s63c-n7_u4s6">做出改变...</string>
  <string mz="text_tips0" name="rl7u9y2lmdwau-n12_djob">请输入您的真实游戏账号！</string>
  <string mz="text_accouont" name="rl7u9y2lmdwau-n3_pxc1-prompt">[color=#818181]输入您的帐号[/color]</string>
  <string mz="btn_guest" name="rl7u9y2lmdwau-n13_wb9d">访客访问</string>
  <string mz="btn_close" name="rl7u9y2lmdwau-n14_wb9d">没变</string>
  <string mz="text_title" name="rl7u9y2ll3r63j-n3_ntzg">免费奖励</string>
  <string mz="text_tips0" name="rl7u9y2ll3r63j-n4_ntzg">选择您想要获得奖励的游戏！</string>
  <string mz="text_tips1" name="rl7u9y2ll3r63j-n10_pjbr">确认后无法更改游戏！</string>
  <string mz="text_account" name="rl7u9y2lmdwaz-n53_wb9d">987654321@qq.com</string>
  <string mz="text_guestAccount" name="rl7u9y2lmdwaz-n57_ntzg">访客帐户</string>
  <string mz="info" name="rl7u9y2lmdwa13-n1_v981">你可以改变你想要的游戏。</string>
  <string mz="info" name="rl7u9y2lmdwa13-n1_v981-texts_0">你可以改变你想要的游戏。</string>
  <string mz="info" name="rl7u9y2lmdwa13-n1_v981-texts_1">您可以在提交订单前更改帐户。</string>
  <string mz="info" name="rl7u9y2lmdwa13-n1_v981-texts_2">获得足够的钻石来赢取奖励，也可以完成挑战赢取奖励。</string>
  <string mz="info" name="rl7u9y2lmdwa13-n1_v981-texts_3">立即玩游戏并赢取奖励！</string>
  <string mz="text_title" name="rl7u9y2lmciw3z-n1_mciw">绑定</string>
  <string mz="text_gameName" name="rl7u9y2lmciw3z-n9_pjbr">绝地求生</string>
  <string mz="text_tips0" name="rl7u9y2lmciw3z-n8_mciw">绑定你的{gameName=PUBG}账号，让你提取的币准确分配到你的账号</string>
  <string mz="btn_bind" name="rl7u9y2lmciw3z-n5_mciw">绑定</string>
  <string mz="btn_later" name="rl7u9y2lmciw3z-n6_mciw">之后</string>
  <string mz="text_title" name="rl7u9y2lmciw40-n1_mciw">成功</string>
  <string mz="text_title" name="rl7u9y2lmciw40-n1_mciw-texts_0">失败的</string>
  <string mz="text_title" name="rl7u9y2lmciw40-n1_mciw-texts_def">成功</string>
  <string mz="text_gameName" name="rl7u9y2lmciw40-n10_pjbr">绝地求生</string>
  <string mz="text_tips0" name="rl7u9y2lmciw40-n8_mciw">绑定成功！
现在玩游戏并收集货币！</string>
  <string mz="text_tips0" name="rl7u9y2lmciw40-n8_mciw-texts_0">绑定成功！
现在玩游戏并收集货币！</string>
  <string mz="text_tips0" name="rl7u9y2lmciw40-n8_mciw-texts_1">绑定失败！
未检测到{gameName=PUBG} APP，请稍后绑定</string>
  <string mz="btn_confirm" name="rl7u9y2lmciw40-n5_mciw">确认</string>
  <string mz="text_account" name="rl7u9y2lmdwa18-n15_x8xq">111@outlook.com</string>
  <string mz="text_title" name="rl7u9y2lmdwa18-n19_w8q4">帐户</string>
  <string mz="text_tips0" name="rl7u9y2lmdwa18-n7_wlb4">链接成功！
立即赢取奖励！</string>
  <string mz="btn_continue" name="rl7u9y2lmdwa18-n3_pxc1">继续</string>
  <string mz="text_tips0" name="rl7u9y2lmciw3y-n3_mciw">您确定要兑换到此帐户吗？</string>
  <string mz="text_account" name="rl7u9y2lmciw3y-n5_mciw">helloworld@outlook.com</string>
  <string mz="btn_confirm" name="rl7u9y2lmciw3y-n6_mciw">确认</string>
  <string mz="btn_change" name="rl7u9y2lmciw3y-n7_mciw">更改帐户</string>
  <string mz="text_title" name="rl7u9y2lmdwa1f-n18_navc">成功的</string>
  <string mz="text_tips0" name="rl7u9y2lmdwa1f-n8_nzkm">完成所有任务并赢得此奖励！</string>
  <string mz="btn_next" name="rl7u9y2lmdwa1f-n1_pxc1">好的</string>
  <string mz="text_title" name="rl7u9y2lu4s63e-n4_u4s6">赎回</string>
  <string mz="text_tips0" name="rl7u9y2lu4s63e-n5_u4s6">连接服务器...</string>
  <string mz="text_tips1" name="rl7u9y2lu4s63e-n6_u4s6">提交订单...</string>
  <string mz="text_tips2" name="rl7u9y2lu4s63e-n7_u4s6">订单审核...</string>
  <string mz="title" name="3ajwo69pqj6mf4j-n4_lq0a">宣称</string>
  <string mz="title" name="3ajwo69pqj6mf47-n4_10cvf">不，谢谢</string>
  <string mz="title" name="3ajwo69pqj6mf3x-n5_e8og">收到</string>
  <string mz="text_value" name="3ajwo69pqj6mf42-n2_eimb">×{count=4}</string>
  <string mz="text_title" name="3ajwo69pqj6mf3u-n33_ntzg">大组合</string>
  <string mz="text_rate" name="3ajwo69pqj6mf3u-n40_illt">{abc=RATE}</string>
  <string mz="text_mutiple" name="3ajwo69pqj6mf3u-n36_ntzg">x5</string>
  <string mz="btn_coliect" name="3ajwo69pqj6mf3u-n3_e8og">收到</string>
  <string mz="text_pbTips" name="3ajwo69pqj6mf3u-n44_u4s6">收集足够兑换！</string>
  <string mz="text_title" name="3ajwo69pmciwf4u-n18_ntzg">组合</string>
  <string mz="btn_claim" name="3ajwo69pmciwf4u-n14_lq0a">宣称</string>
  <string mz="text_pbTips" name="3ajwo69pmciwf4u-n26_u4s6">收集足够兑换！</string>
  <string mz="text_title" name="3ajwo69pqj6mf48-n9_lq0a">升级</string>
  <string mz="text_pbTips" name="3ajwo69pqj6mf48-n19_u4s6">收集足够兑换！</string>
  <string mz="text_pbTips" name="3ajwo69pmciwf4t-n15_mciw">收集足够兑换！</string>
  <string mz="text_title" name="3ajwo69pqj6mf4k-n18_ntzg">恭喜</string>
  <string mz="btn_claim" name="3ajwo69pqj6mf4k-n14_lq0a">宣称</string>
  <string mz="text_pbTips" name="3ajwo69pqj6mf4k-n26_u4s6">收集足够兑换！</string>
  <string mz="title" name="ayq1m1qumciw0-n1_mciw">玩游戏收集</string>
  <string mz="title" name="ayq1m1qumciw2-n3_mciw">赎回</string>
  <string mz="text_title" name="ayq1m1qumciw41-n1_mciw">给你惊喜</string>
  <string mz="text_leftTips" name="ayq1m1qumciw41-n2_mciw">剩下的时间：</string>
  <string mz="text_timeShow" name="ayq1m1qumciw41-n6_mciw">您可以在 [color=#FFD600]{time=48} 小时[/color] 后获得这些奖励</string>
  <string mz="text_maxWin" name="ayq1m1qumciw41-n13_mciw">最大胜利 [color=#FFD600]{max=9999}[/color]</string>
  <string mz="text_getTips" name="ayq1m1qumciw41-n15_mciw">尽可能多地收集</string>
  <string mz="text_title" name="ayq1m1qumciw42-n4_mciw">结束</string>
  <string mz="text_tips0" name="ayq1m1qumciw42-n14_mciw">立即领取您的奖励！
并发现更多惊喜！</string>
  <string mz="title" name="a1jbnm9hmciw2-n11_djob">&lt;img src=ui://9gpz896kdjob26&gt;帐户</string>
  <string mz="title" name="a1jbnm9hr4ip49-n4_r4ip">确认</string>
  <string mz="title" name="a1jbnm9hmciw0-n17_pxdq">赎回</string>
  <string mz="title_value" name="a1jbnm9he31h3t-n4_e31h">{chip=999}&lt;img src=ui://9gpz896kpjbras width=32 height=32&gt;兑换</string>
  <string mz="title" name="a1jbnm9hmciw1-n3_pxc1">提交图层</string>
  <string mz="text_tips0" name="a1jbnm9he31h3r-n5_lln7">在 14 个工作日内发送到您的帐户</string>
  <string mz="text_account" name="a1jbnm9he31h3u-n53_wb9d">987654321@qq.com</string>
  <string mz="text_guestAccount" name="a1jbnm9he31h3u-n57_ntzg">客人账户</string>
  <string mz="text_account" name="a1jbnm9hmciw3w-n5_mciw">helloworld@outlook.com</string>
  <string mz="text_tips0" name="a1jbnm9hmciw3w-n3_mciw">您确定要兑换到此帐户吗？</string>
  <string mz="btn_confirm" name="a1jbnm9hmciw3w-n6_mciw">确认</string>
  <string mz="btn_change" name="a1jbnm9hmciw3w-n7_mciw">更改帐户</string>
  <string mz="text_title" name="a1jbnm9hmciw3x-n10_lln7">成功的</string>
  <string mz="text_tips1" name="a1jbnm9hmciw3x-n3_mciw">奖励将在 14 个工作日内发送到您的账户</string>
  <string mz="text_title" name="a1jbnm9hmdwa1g-n9_w8q4">提示</string>
  <string mz="text_tips0" name="a1jbnm9hmdwa1g-n8_wb9d">你现在是客人。</string>
  <string mz="text_tips1" name="a1jbnm9hmdwa1g-n6_nzkm">您必须关联您的帐户才能兑换奖励</string>
  <string mz="btn_confirm" name="a1jbnm9hmdwa1g-n1_pxc1">关联</string>
  <string mz="text_title" name="fmr5mo8pg5fl1k-n30_e5ju">道具</string>
  <string mz="text_tips0" name="fmr5mo8pg5fl1k-n6_kft3">点击数字积木到负 1</string>
  <string mz="text_tips0" name="fmr5mo8pg5fl1k-n6_kft3-texts_0">点击数字积木加 2</string>
  <string mz="text_tips0" name="fmr5mo8pg5fl1k-n6_kft3-texts_1">点击一个数字砖来摧毁</string>
  <string mz="text_tips0" name="fmr5mo8pg5fl1k-n6_kft3-texts_def">点击数字积木到负 1</string>
  <string mz="n4" name="tiosr750e9kl1-n4_e9kl">出口</string>
  <string mz="title" name="tiosr750p3x0k1l-n1_p3x0">审查</string>
  <string mz="text_title" name="tiosr750e9kl0-n34_e5ju">游戏结束</string>
  <string mz="text_title" name="7xruccmafntl0-n36_mfgs">反馈</string>
  <string mz="text_tips0" name="7xruccmafntl0-n28_nop9">评价我们，让我们变得更好</string>
  <string mz="title" name="94fbq9npw8q42q-n1_w8q4">确认</string>
  <string mz="title" name="94fbq9nppjbr2c-n1_pjbr">锤子</string>
  <string mz="title" name="94fbq9nppjbr2c-n1_pjbr-texts_0">增加</string>
  <string mz="title" name="94fbq9nppjbr2c-n1_pjbr-texts_1">锤子</string>
  <string mz="title" name="94fbq9nppjbr2b-n1_pjbr">赎回</string>
  <string mz="title" name="94fbq9nppjbr27-n1_pjbr">皮肤</string>
  <string mz="text_level" name="94fbq9nppjbr27-n4_pjbr">等级{unlockSkinLevel=5}</string>
  <string mz="info" name="94fbq9npw8q42p-n9_ht85">您可以免费赢得游戏皮肤</string>
  <string mz="text_title" name="zrdho07jotfn34-n17_sulh">提示</string>
  <string mz="text_content" name="zrdho07jotfn34-n2_naor">此功能尚不可用！</string>
  <string mz="info" name="usopam3mxewn1-n2_lix2">完成任务即可获得此奖励！</string>
  <string mz="info" name="usopam3mxewn1-n2_lix2-texts_0">完成任务即可获得此奖励！</string>
  <string mz="info" name="usopam3mxewn1-n2_lix2-texts_1">您还可以收集货币来兑换其他奖励！</string>
  <string mz="info" name="usopam3mxewn1-n2_lix2-texts_2">收集足够的碎片来兑换你最喜欢的皮肤！</string>
  <string mz="info" name="usopam3mxewn1-n2_lix2-texts_3">立即玩游戏以免费收集碎片！</string>
  <string mz="txt" name="v5jd19r68d5zh-n54_ilew">英语</string>
  <string mz="txt" name="v5jd19r68d5zo-n61_ilew">英语</string>
  <string mz="title" name="v5jd19r6fi6if-n1_fi6i">广告</string>
  <string mz="on" name="v5jd19r6fi6i2-n8_wwb2">开启</string>
  <string mz="off" name="v5jd19r6fi6i2-n9_wwb2">关闭</string>
  <string mz="title" name="v5jd19r6fi6i2-n12_fi6i">广告过滤</string>
  <string mz="n14" name="v5jd19r6fi6i1-n14_l0se">工具</string>
  <string mz="btn_adSetting" name="v5jd19r6fi6i1-n4_waaa">广告过滤</string>
  <string mz="btn_open_exchange" name="v5jd19r6fi6i1-n49_8d5z">兑换开启</string>
  <string mz="btn_addGold1" name="v5jd19r6fi6i1-n21_fi6i">+5000金币、+500碎片</string>
  <string mz="btn_addGold2" name="v5jd19r6fi6i1-n27_fi6i">+50000金币</string>
  <string mz="btn_addLevel" name="v5jd19r6fi6i1-n37_fi6i">+1等级</string>
  <string mz="btn_addVideo" name="v5jd19r6fi6i1-n36_fi6i">+1视频</string>
</resources>